crypto_data_downloader/__init__.py
crypto_data_downloader/binance.py
crypto_data_downloader/utils.py
crypto_data_downloader-0.1.7.dist-info/METADATA
crypto_data_downloader-0.1.7.dist-info/WHEEL
crypto_data_downloader-0.1.7.dist-info/top_level.txt
crypto_data_downloader-0.1.7.dist-info/RECORD
