Metadata-Version: 2.4
Name: crypto-data-downloader
Version: 0.1.7
Summary: High-speed cryptocurrency OHLCV data downloader via concurrent API requests
Home-page: https://github.com/SerenaTradingResearch/crypto-data-downloader
Author: Ricky Ding
Author-email: e0134117@u.nus.edu
License: MIT
Keywords: crypto,binance,ohlcv,market-data,downloader
Classifier: Programming Language :: Python :: 3
Classifier: Intended Audience :: Financial and Insurance Industry
Classifier: License :: OSI Approved :: MIT License
Requires-Python: >=3.8
Requires-Dist: matplotlib
Requires-Dist: numpy
Requires-Dist: aiohttp
Dynamic: author
Dynamic: author-email
Dynamic: classifier
Dynamic: description
Dynamic: description-content-type
Dynamic: home-page
Dynamic: keywords
Dynamic: license
Dynamic: requires-dist
Dynamic: requires-python
Dynamic: summary
